prsaw2/__init__.py
prsaw2/client.py
prsaw2/errors.py
prsaw2/objects.py
prsaw2-0.42.dist-info/LICENCE
prsaw2-0.42.dist-info/METADATA
prsaw2-0.42.dist-info/WHEEL
prsaw2-0.42.dist-info/top_level.txt
prsaw2-0.42.dist-info/RECORD
