Metadata-Version: 2.1
Name: prsaw2
Version: 0.42
Summary: Stands for Python random api wrapper version 2.
Home-page: https://github.com/FlamptX/prsaw2
Author: Flampt
License: UNKNOWN
Keywords: python,api,rsa
Platform: UNKNOWN
Classifier: Programming Language :: Python :: 3
Classifier: License :: OSI Approved :: MIT License
Classifier: Operating System :: OS Independent
Requires-Python: >=3.6
License-File: LICENCE
